{"data":{"wordpressPost":{"title":"Kun 2000 festivalpass igjen til Øya","date":"21st April 2010","content":"<p>Vi jobber med å gjøre Øya-opplevelsen enda bedre og kreativiteten er stor på Øya-kontoret om dagen. Neste uke slippes flere artister til sommerens store musikkfest i Middelalderparken. I første halvdel av juni vil årets program være komplett.</p>\n<p>Mange artister er ennå ikke plassert på dag, men dette vil bli gjort om ikke lenge. Foreløpig er disse satt på dato</p>\n<p>ONS 11/8: M.I.A. / Iggy &#038; The Stooges / Air / The Gaslight Anthem / Raekwon / Fucked Up / Serena Maneesh / Shining / Imperial State Electric</p>\n<p>TORS 12/8: Pavement / Jonsi / LCD Soundsystem / Against Me! / Casiokids / Kråkesølv / Baroness / Miike Snow</p>\n<p>FRE 13/8: Robyn / La Roux / Girls / Major Lazer / Marina &#038; The Diamonds / Tune-Yards</p>\n<p>LØR 14/8: Big Boi / Paul Weller / Karpe Diem / The xx / Converge / Tony Allen / Local Natives / Cymbals Eat Guitars</p>\n","wordpress_id":410,"translations":{"nb":{"url":"/2010/04/21/kun-2000-festivalpass-igjen-til-%c3%b8ya/"},"en":null}}},"pageContext":{"isCreatedByStatefulCreatePages":false,"id":"5834bff8-7848-5537-8770-9eb139c87fce"}}