{"data":{"wordpressPost":{"title":"Viktig info til alle med Øya-billett","date":"5th August 2011","content":"<p>Åpningstidene er:<br />\nman 8. aug, kl 13-20<br />\ntirs 9. aug, kl 12-22</p>\n<p>Vi minner også om at man må ha bytta fra billett til armbånd for å komme gratis inn på Klubbdagen tirsdag 9. august, som er inkludert i femdagerspasset.</p>\n<p>OBS<br />\nPå Youngstorget må man møte opp personlig for å bytte billetten sin til armbånd, da det må vises ID (i forhold til alder). Armbånd blir satt på i boden på Youngstorget.</p>\n"}},"pageContext":{"isCreatedByStatefulCreatePages":false,"id":"c7c6d2b2-03dd-5de4-8e57-a84ed562a4bc"}}