{"data":{"wordpressPost":{"title":"Festivalmagasinet er på gata","date":"13th July 2011","content":"<p>Nå kan du finne årets festivalmagasin på de beste barene, konsertlokalene og caféene i de største byene i landet. Festivalmagasinet er i år i et litt mindre format, slik at du får plass til det i lomma. Her finner du en masse nyttig Øya-info, programoppsettet, tips, festivalkart og selvsagt presentasjoner av artistene. Med andre ord kan du slappe av med over 100 sider godt festivalstoff, mens du gleder deg til eller planlegger Øyafestivalen 2011.</p>\n","wordpress_id":15458,"translations":{"nb":{"url":"/2011/07/13/festivalmagasinet-er-pa-gata/"},"en":null}}},"pageContext":{"isCreatedByStatefulCreatePages":false,"id":"1ce50198-82e8-5d5e-9950-da5b995d8b08"}}