{"data":{"wordpressPost":{"title":"Første artister til GSF Skatepark er klare","date":"26th May 2010","content":"<p>Made In China<br />\nMade In China, en perle fra østkanten i Oslo, har tross sin unge alder (17-18) spilt sammen i fire år. De er oppvokst på Grorud og har skrevet det som av noen kalles Groruds nasjonalsang. ”Alt er Made In China, så da er faen meg vi det og!&raquo;</p>\n<p>Honningbarna<br />\n17åringene fra Kristiansand har sveipet over landet med uimotståelig sjarm og absolutt forakt for det etablerte. Harde som sement, søte som konfekt &#8211; Honningbarna er seks 17 år gamle gutter som spiller pønk med cello og hammondorgel.<br />\n”URØRT”:http://www.nrk.no/urort/Artist/Honningbarna/default.aspx</p>\n<p>Vinnie Who (DK)<br />\nDanske Vinnie Who spilte by:Larm og siden har de gjort en hel haug konserter i Norge &#8211; fra Bergen til Kristiansand. De spiller fengende disko-house og kan sjekkes ut her: ”MYSPACE”:http://www.myspace.com/vinniewhoofficial</p>\n<p>Megaphonic Thrift<br />\nEn gang i tiden hadde Juvenile Rock Club en avstemning om hvilke band publikum hadde lyst til å se og Megaphonic lå helt øverst! Det har tatt tid før vi har fått det til, men nå kommer de endelig og vi gleder oss innmari. Megaphonic gjør det stort både i inn- og utland og slapp tidligere i år plata Decay Decoy, et sonisk mesterverk.<br />\n“MYSPACE”:http://www.myspace.com/megaphonicthrift</p>\n"}},"pageContext":{"isCreatedByStatefulCreatePages":false,"id":"1a72f4a7-c487-5bee-afae-a61a8dcea9b1"}}