{"data":{"wordpressPost":{"title":"Festivalmagasinet er her!","date":"17th July 2013","content":"<p>Plukk opp årets Øyamagasin. Her har du masse godt og nyttig lesestoff i de siste ukene før festivalstart. Les om artister og generell Øyainfo. I tillegg finner du stoff om Øyanatt, Klubbdagen, Øyakino, festivalmaten, vår miljøsatsing og våre samarbeidspartnere. Kart over området og programmet finner du også. Det kan være greit å merke seg at noen av spilletidene på Klubben torsdag og lørdag er justert litt etter at magasinet gikk i trykken. Helt korrekte spilletider finner du alltid på nettsidene og i appen, som er rett rundt hjørnet.</p>\n<p>&nbsp;</p>\n<p>Øyamagasinet finner du på klubbene vi samarbeider med, hos Choice-hotellene i Oslo, Hi-Fi Klubben og Carlings</p>\n","wordpress_id":8037,"translations":{"nb":{"url":"/2013/07/17/festivalmagasinet-er-her/"},"en":null}}},"pageContext":{"isCreatedByStatefulCreatePages":false,"id":"8f3ecffc-8ebc-59a3-bbcb-e6cf70ad0e8a","locale":"nb"}}