{"data":{"wordpressPost":{"title":"Klubbdagen snart i gang","date":"2010-08-10T15:16:00.000Z","content":"<p>Om noen få timer sparkes Øyafestivalen 2010 i gang med et imponerende sterkt program på Klubbdagen. 25 scener over hele byen har bidratt til at festivalen får et startskudd uten sidestykke. Klubbdagen er gratis for de med fullt festivalpass, men vi anbefaler deg å komme tidlig om det er noe du MÅ se. Det blir nemlig fort fullt flere steder. Første band ut er Red April på Dattera Til Hagen klokka 17.00 og vi gir oss ikke før 80 band har spilt og de siste tonene til Eskimo avrunder det hele på Tilt utpå natta. Vår anbefaling er som alltid; få med deg mest mulig ny musikk! <a href=\"http://oyafestivalen.com/pages/nor/8-program\" target=\"_blank\">Hele programmet finner du her</a><br />\nVi gleder oss!</p>\n","wordpress_id":271,"translations":{"nb":{"url":"/2010/08/10/klubbdagen-snart-i-gang/"},"en":null}}},"pageContext":{"isCreatedByStatefulCreatePages":false,"id":"dda468f7-c640-566a-b4a2-dc6bd0d86914","locale":"nb"}}