{"data":{"wordpressPost":{"title":"Øyanatt: Nicky William på Bortenfor","date":"25th June 2018","content":"<p>Torsdag 9. august</p>\n<p><strong>Øyanatt // Nicky William (SE) // Bortenfor</strong><br />\nCC: GRATIS!<br />\nID 20</p>\n<p>Vi så Nicky William live i Oslo under årets by:Larm og ble blåst i bakken!<br />\nNå gleder vi oss til til et intimt sett på Bortenfor under Øya.</p>\n<p>Låtskriveren Nicky William ble født i Oxelösund i 1995 med stor kjærlighet til musikk, og allerede i løpet av sine tenår skapte han det karakteristiske utrykket, med sin skjelvende dype stemme, enkle og effektive gitarspill og tekster levert med en gammel sjels karakter.</p>\n<p>Er du fan av artister som Joni Mitchell, Bob Dylan, Leonard Cohen, Patti Smith, Nick Cave eller mer moderne artister som Radiohead, St. Vincent, Andrew Bird, Fiona Apple, Wilco?</p>\n<p>Da sees vi etter Øya lukker portene på torsdagen!</p>\n<p><a href=\"https://www.facebook.com/Nickywilliamofficial/?fref=mentions\">www.facebook.com/Nickywilliamofficial</a></p>\n<p>OM ØYANATT: Øyanatt er konserter og klubbkonsepter rundt omkring i Oslo sentrum etter at Tøyenparken stenger 23.00. Dette er altså en glimrende mulighet til å ta med seg den gode festivalstemninga inn i byen etterpå. Øyanatt lages i samarbeid med de beste arrangørene og klubbene i Oslo. Grunnet varierende forutsetninger og behovet for at arrangørene skal få disse konsertene/klubbkonseptene til å gå rundt på egenhånd, gjør det ikke mulig å inkludere Øyanatt i festivalpasset. Gyldig Øya-billett til den aktuelle dagen (evt ukespass) gir rabatt på Øyanatt-arrangement.</p>\n","wordpress_id":22008,"translations":{"nb":{"url":"/2018/06/25/oyanatt-nicky-williams-pa-bortenfor/"},"en":null}}},"pageContext":{"isCreatedByStatefulCreatePages":false,"id":"64a98969-038f-5b41-95f2-55b0ada9022c","locale":"nb"}}