{"data":{"wordpressPost":{"title":"Øya utnevnt til energi-pionér","date":"1st October 2014","content":"<p>EE Music har offentliggjort <a href=\"//ee-music.eu/?id=343\">15 europeiske musikkfestivaler</a> som de mener er pionerer innenfor energiområdet. Øyafestivalen er med som eneste nordiske musikkfestival. Øyas fokus på utslippsfri festivalenergi og energieffektiviseringstiltak blir særlig trukket frem.</p>\n<p>&#8211; I Øya har vi jobbet målrettet med å redusere vår miljøbelastning innenfor en rekke områder, der energibruk har vært en sentral del hvor vi har lagt ned mye arbeid. Derfor er det veldig givende å få denne typen oppmerksomhet, sier Ingrid Kleiva Møller, miljøsjef i Øyafestivalen.</p>\n<p><b>Fra fossilt til fornybart<br />\n</b>Allerede i 2009 satte Øyafestivalen i gang med å gå over fra forurensende dieselaggregat og over på strøm fra fastnettet. I 2010 ble det bygget en ny trafostasjon og lagt ned nye strømkabler og koblingspunkt i Middelalderparken. Dette la til rette for at festivalen for første gang kunne drives 100 prosent fra fastnettet og bidro til at festivalen ble 80% mer energieffektiv.</p>\n<p><b>Fornybart på Tøyen<br />\n</b>Da festivalen flyttet til et nytt område var energiforsyning en sentral utfordring. Tøyenparken hadde ikke nok strømkapasitet for festivalen, og det måtte investeres i nye strømkabler og trafostasjon på området.</p>\n<p>&#8211; For oss var det uaktuelt å gå tilbake til forurensende dieselaggregater. Denne investeringen vil også komme Miniøya og andre arrangører i parken til gode, sier Kleiva Møller.</p>\n<p><b>Effektiv energibruk<br />\n</b>Til tross for at festivalen drives på miljøvennlig strøm jobbes det mye med å redusere energibruken så mye som mulig. De siste årene har strømforbruket gått jevnt nedover og festivalen bruker nå omtrent like mye strøm som to norske husstander gjør i løpet av ett år.</p>\n<p><b>Om EE Music<br />\n</b>Musikkinitiativet EE Music jobber for å øke fokuset på energieffektive musikkopplevelser i hele Europa. Det er startet opp av blant annet Julie’s Bicycle (UK) og Green Music Initiative (DE) og er finansiert av EUs Intelligente Energi Europa program (IEE).</p>\n<p>Foto: Steffen Rikenberg</p>\n"}},"pageContext":{"isCreatedByStatefulCreatePages":false,"id":"d19a8875-d4ce-5bc4-a081-6dab7c21d260"}}