{"data":{"wordpressPost":{"title":"Under 900 fredagsbilletter igjen","excerpt":"<p>Billetsalget til Øyafestivalen går virkelig unna. Nå er det under 900 dagsbilletter igjen til fredag 12. august. Det betyr at det snart ikke vil være flere fredagsbilletter igjen. Fra før er Øya tomme for fulle femdagerspass og onsdagsbilletter. Sjøl om fredagsbillettene går fortest for øyeblikket, ligger både torsdagen og lørdagen svært tett bak. Det betyr at dersom du vil sikre deg noen dager i Middelalderparken under Øya, må du skaffe deg billetter snart. Vi venter nå på de aller siste artistbekreftelsene og regner med å kunne presentere komplett program i løpet av neste uke.<br />\n<a href=\"http://www.billettservice.no/artist/oyafestivalen-billetter/301563\" target=\"_blank\">KJØP BILLETTER HER</a></p>\n","content":"<p>Her er noen av mange høydepunkter på de dagene det er billetter igjen til</p>\n<p>TORS 11/8: Kaizers Orchestra spiller Violeta Violeta vol 2, Fleet Foxes, Aphex Twin, Hercules &#038; Love Affair, Guided By Voices, Wiz Khalifa, Explosions In The Sky, Q-Tip, Janelle Monae, Graveyard, Honningbarna, Real Ones</p>\n<p>FRE 12/8: Pulp, Kvelertak, The Jayhawks, Lykke Li, Bring Me The Horizon, Mayer Hawthorne &#038; The County, OFF!, Wannskrækk, Noah &#038; The Whale, Montée, 120 Days, Turns, Ghost</p>\n<p>LØR 13/8: Håkan Hellström, Kyuss Lives!, The Avett Brothers, Fjorden Baby!, Mari Boine, Jamie xx, Stein Torleif Bjella, Rumble In Rhodos, Maria Mena, Hurra Torpedo, Kitchie Kitchie Ki Me O, Comeback Kid</p>\n<p><a href=\"http://oyafestivalen.com/pages/nor/8-program\" target=\"_blank\">SE FORELØPIG PROGRAM HER</a></p>\n","date":"2011-06-15T09:05:49.000Z","wordpress_id":136,"featured_image":null,"translations":{"nb":{"url":"/2011/06/15/under-900-fredagsbilletter-igjen/"},"en":null}}},"pageContext":{"isCreatedByStatefulCreatePages":false,"id":"064b51ef-a8ad-513b-a5b3-832fc701e63a","locale":"nb"}}