{"pageContext":{"isCreatedByStatefulCreatePages":false,"group":[{"node":{"id":"1a0dc1e7-cdd7-536f-a04d-14bd0a9f50a3","slug":"mot-fire-oya-artister-pa-hi-fi-scenen","title":"Møt fire Øya-artister på Hi-Fi Scenen","date":"2015-08-10T11:48:12.000Z","excerpt":"<p>Shamir, Silvana Imam, Emilie Nicolas og Jaga Jazzist forteller om sitt arbeid med musikk og lyd.</p>\n"}},{"node":{"id":"942ae7f3-2969-5b0b-bc12-354aa804b8b5","slug":"popquiz-i-biblioteket","title":"Popquiz i Biblioteket","date":"2015-08-10T09:26:56.000Z","excerpt":"<p>Fredag kan du teste kunnskapene og høre to generasjoner Greni fortelle om musikkbyen Oslo. </p>\n"}},{"node":{"id":"926dd146-4bab-5480-9d3f-8d6e97925dc8","slug":"oyaprat-9-torgeir-waldemar","title":"Øyaprat 9: Torgeir Waldemar","date":"2015-08-10T06:35:07.000Z","excerpt":"<p>Torgeir Waldemar spiller i Amfiet, torsdag 13. august klokka 14:15.</p>\n"}},{"node":{"id":"5c79d0bc-49f1-5666-ae0e-034b61e21b89","slug":"nybygd-nett-under-oya","title":"Nybygd nett under Øya","date":"2015-08-09T16:59:22.000Z","excerpt":"<p>Broadnet bidrar til at både publikum og de som jobber på Øya får god tilgang til nett.</p>\n"}},{"node":{"id":"0be6120e-8a9c-5ec9-a71e-db98fccc0ac2","slug":"opplev-verdens-beste-lydanlegg-pa-oya","title":"Opplev verdens beste lydanlegg på Øya","date":"2015-08-09T12:22:51.000Z","excerpt":"<p>Hi-Fi Klubben som stiller med verdens beste lydanlegg fra Bowers &amp; Wilkins</p>\n"}},{"node":{"id":"4ae644d1-b49e-5a96-9a9b-9229f7b593a0","slug":"spillelister-dag-for-dag-fra-tidal","title":"Spillelister: dag for dag fra TIDAL","date":"2015-08-09T07:45:06.000Z","excerpt":"<p>TIDAL har satt sammen en spilleliste for hver enkelt dag.</p>\n"}},{"node":{"id":"09f9d92f-afa5-5129-8e8a-b4d5159b8b21","slug":"bytt-billetten-i-armband-pa-forhand-2","title":"Bytt billetten i armbånd på forhånd","date":"2015-08-08T11:45:29.000Z","excerpt":"<p>Ikke kast bort tid i kø rett før første konserten du MÅ ha med deg</p>\n"}},{"node":{"id":"261a9973-d34b-5b9a-99b5-9716919cc517","slug":"ringnes-runde-bord-pa-oya","title":"Ringnes’ Runde Bord på Øya","date":"2015-08-07T09:51:04.000Z","excerpt":"<p>Ølsmaking hver dag under festivalen, kjøp billetter i Ølparadiset.</p>\n"}},{"node":{"id":"3fd8beb1-1637-5683-b711-fe7ba0ac8b81","slug":"2-x-klubb-yacht-rock-pa-oyanatt","title":"2 x Klubb Yacht Rock på Øyanatt","date":"2015-08-06T20:34:07.000Z","excerpt":"<p>Rockefeller både torsdag og fredag</p>\n"}},{"node":{"id":"c0c45655-711d-54fe-921a-d7e6ad9da774","slug":"oyaprat-8-the-good-the-bad-and-the-zugly","title":"Øyaprat 8: The Good The Bad And The Zugly","date":"2015-08-06T08:24:12.000Z","excerpt":"<p>The Good The Bad And The Zugly spiller på Hagen, fredag 14. august, klokka 21:20</p>\n"}}],"pathPrefix":"posts","first":false,"last":false,"index":51,"pageCount":183,"additionalContext":{}}}