{"pageContext":{"isCreatedByStatefulCreatePages":false,"group":[{"node":{"id":"c5986c9d-fb24-52fd-b5c1-6c85e294f231","slug":"oya-london-18-april","title":"Øya i London 18. april","date":"2018-03-06T10:07:25.000Z","excerpt":"<p>Vi tar med oss Sassy009 og Pom Poko til Birthdays i Dalston. </p>\n"}},{"node":{"id":"3dc67d27-e8f7-5f88-82f6-fe067901f084","slug":"vaer-med-pa-a-lage-oya-2018","title":"Vær med på å lage Øya 2018!","date":"2018-03-05T12:38:38.000Z","excerpt":"<p>Frivilligregistreringa er åpen</p>\n"}},{"node":{"id":"552bbb54-98d5-53b5-9672-fe7732ee3c5d","slug":"fire-norske-oya","title":"Fire norske til Øya","date":"2018-03-05T09:48:38.000Z","excerpt":"<p>Emir, Halie, Linni og Rohey!</p>\n"}},{"node":{"id":"369d7a6f-aae2-52f7-9c40-7978472adc31","slug":"behemoth-bokassa-oya-torsdag-9-8","title":"Behemoth og Bokassa til Øya torsdag 9/8","date":"2018-02-28T08:49:12.000Z","excerpt":"<p>To band med ulikt utgangspunkt for å spille kjapt og hardt kommer til Tøyenparken torsdag 9. august. </p>\n"}},{"node":{"id":"e857ad4a-149e-5185-84c1-0c35fe7ab410","slug":"forste-slipp-hi-fi-klubben","title":"Første slipp til Hi-Fi Klubben","date":"2018-02-27T08:52:38.000Z","excerpt":"<p>En vaskeekte jungle-legende, en av landets beste DJs, og to utforskende norske artister vi digger!</p>\n"}},{"node":{"id":"83494bf1-c15e-5b3b-ab72-04ebbf7f8a16","slug":"alex-cameron-the-comet-is-coming-oya","title":"Alex Cameron og The Comet Is Coming til Øya","date":"2018-02-21T08:44:34.000Z","excerpt":"<p>&nbsp; ALEX CAMERON (AU) – lørdag 11. august THE COMET IS COMING (UK) – onsdag 8. august Øya-programmet fylles opp av en god blanding med etablerte favoritter og musikere du kanskje ikke kjenner fra før. Australske Alex Cameron hadde et aktivt 2017 med låtskriving for The Killers og et solid album på egenhånd. Fra Londons [&hellip;]</p>\n"}},{"node":{"id":"2b8e02bb-53b4-57dd-b76f-cbaaf42fa417","slug":"kultbandet-witch-oya","title":"Kultbandet WITCH til Øya","date":"2018-02-20T08:50:21.000Z","excerpt":"<p>For første gang i Norge fredag 10. august!</p>\n"}},{"node":{"id":"b3239f72-7f43-5473-8fa1-be4130ee9283","slug":"slotface-curtis-harding-oya","title":"Sløtface og Curtis Harding til Øya","date":"2018-02-14T08:47:33.000Z","excerpt":"<p>Sløtface og Curtis Harding leverte hvert sitt sterke album i fjor og er selvsagte valg til vårt varierte Øya-program. Vi kommet til å ha jevnlige artistslipp gjennom hele våren, så følg med.</p>\n"}},{"node":{"id":"c4b71fe9-7fcc-5af0-9d58-ce927c62db4a","slug":"to-nye-oya","title":"To nye til Øya","date":"2018-02-13T08:49:45.000Z","excerpt":"<p>STEAMDOME – fre 10. aug / KING GIZZARD &#038; THE LIZARD WIZARD (AU) – tors 9. aug</p>\n"}},{"node":{"id":"0c242e9e-1c7f-5c38-8eeb-1b728adb1e0a","slug":"jenny-lewis-phoebe-bridgers-oya-onsdag-8-8","title":"Jenny Lewis og Phoebe Bridgers til Øya onsdag 8/8","date":"2018-02-07T08:55:22.000Z","excerpt":"<p>Under 3500 ukespass igjen!</p>\n"}}],"pathPrefix":"posts","first":false,"last":false,"index":17,"pageCount":183,"additionalContext":{}}}