{"data":{"wordpressPost":{"title":"Aldersgrenser &#8211; Klubbdagen 11/8","date":"21st July 2009","content":"<p>Under årets Klubbdag vil det være tilbud for omtrent alle aldersgrupper. Under finner du en oversikt over de ulike aldersgrensene for Klubbdagen.</p>\n<p>Klubbdagen er gratis for alle med festivalpass, men mange av stedene fylles opp tidlig, så møt opp i god tid.</p>\n<p>*FRI ALDERSGRENSE*<br />\nEldorado kino<br />\nJuvenile Rock Club (kun for de fra 13 t.o.m. 18)<br />\nSpirit på SubScene<br />\nKonsert på Trikken<br />\nNasjonalmuseet (Tullinløkka)</p>\n<p>*18 ÅR*<br />\nBlå<br />\nElm Street<br />\nGamla<br />\nGarage<br />\nInternasjonalen<br />\nJohn Dee<br />\nParkteatret</p>\n<p>*20 ÅR*<br />\n13th Floor Club på Pigalle<br />\nDattera til Hagen<br />\nFisk &#038; Vilt<br />\nFunhouse<br />\nGloria Flames<br />\nKaos<br />\nLast Train<br />\nMir<br />\nMono<br />\nPalace Grill<br />\nRevolver<br />\nSkuret<br />\nSound of MU<br />\nTilt<br />\nThe Villa<br />\nØstkanten Bluesklubb på Herr Nilsen</p>\n"}},"pageContext":{"isCreatedByStatefulCreatePages":false,"id":"4fe38b3d-d7b9-5334-ba81-899a2e849290"}}