{"data":{"wordpressPost":{"title":"Under 1000 ukespass igjen til Øya","date":"2017-04-24T07:59:02.000Z","content":"<p>Det er nå under 1000 ukespass igjen til Øyafestivalen. Vi tror disse vil gå fort unna. Vil du ha med deg hele festivalen, må du være rask. Ukespass inkluderer fire fullpakka dager i Tøyenparken, med aktuell og variert musikk. I tillegg får man gratis inngang på over 20 scener under Klubbdagen tirsdag 8. august, vår tradisjonsrike åpningsdag.</p>\n<p>I tillegg selger dagsbillettene i imponerende tempo, med fredagen som den foreløpig mest populære. De aller fleste artistene er plassert på dager. <a href=\"http://oya.test/program/\">Sjekk her for foreløpig oversikt</a>.</p>\n<p>Vi venter fortsatt på noen bekreftelser, så forvent noen musikalske gladsaker de kommende ukene.</p>\n<p>foto Ihne Pedersen</p>\n","wordpress_id":19820,"translations":{"nb":{"url":"/2017/04/24/1000-ukespass-igjen-oya/"},"en":null}}},"pageContext":{"isCreatedByStatefulCreatePages":false,"id":"8f30e412-d82e-5646-95e7-9724742ccc13","locale":"nb"}}